{
    "generated_at": "2026-07-16 17:07:41",
    "tests": {
        "count": 1572,
        "assertions": 3611,
        "status": "passing"
    },
    "coverage": {
        "lines": 89.93,
        "percentage": 90,
        "html_report": ".coverage\/index.html"
    },
    "phpstan": {
        "level": 8,
        "status": "pass"
    },
    "phpmd": {
        "ran": true,
        "violations": 0,
        "status": "clean"
    },
    "code_style": {
        "ran": true,
        "status": "clean"
    },
    "vitest": {
        "ran": true,
        "count": 30,
        "status": "passing"
    },
    "requirements": {
        "php": ">=8.4",
        "symfony": "^6.4|^7.0|^8.0"
    }
}